README.md
setup.py
pysangkom/__init__.py
pysangkom/forkyou.py
pysangkom.egg-info/PKG-INFO
pysangkom.egg-info/SOURCES.txt
pysangkom.egg-info/dependency_links.txt
pysangkom.egg-info/requires.txt
pysangkom.egg-info/top_level.txt