Metadata-Version: 2.1
Name: pysangkom
Version: 1.0.5
Summary: This library is pysangkom, Please becareful
Author: Meta_Keen
Author-email: vxfqkn8wtx@privaterelay.appleid.com
Classifier: License :: OSI Approved :: MIT License
Classifier: Programming Language :: Python :: 3
Classifier: Programming Language :: Python :: 3.7
Classifier: Programming Language :: Python :: 3.8
Classifier: Programming Language :: Python :: 3.9
Classifier: Programming Language :: Python :: 3.10
Classifier: Programming Language :: Python :: 3.11
